rv32i.v
module riscv_core(
    input wire clk,
    input wire reset,
    output reg [31:0] pc,
    output [31:0] x10
);
    reg [31:0] regs [0:31];      // 32-bit register file (x0 to x31)
    reg [31:0] mem [0:1023];     // 4KB memory (1024 words)
    wire [31:0] instr;           // Current instruction

    assign instr = mem[pc[11:2]]; // Word-aligned fetch
    assign x10 = regs[10];        // Output register a0 (x10)

    wire [6:0] opcode = instr[6:0];
    wire [4:0] rd     = instr[11:7];
    wire [2:0] funct3 = instr[14:12];
    wire [4:0] rs1    = instr[19:15];
    wire [4:0] rs2    = instr[24:20];
    wire [6:0] funct7 = instr[31:25];

    wire [31:0] imm_i = {{20{instr[31]}}, instr[31:20]};
    wire [31:0] imm_s = {{20{instr[31]}}, instr[31:25], instr[11:7]};
    wire [31:0] imm_b = {{20{instr[31]}}, instr[31], instr[7], instr[30:25], instr[11:8], 1'b0};
    wire [31:0] imm_j = {{12{instr[31]}}, instr[19:12], instr[20], instr[30:21], 1'b0};

    integer i; // Declare integer for loop compatibility
    always @(posedge clk or posedge reset) begin
        if (reset) begin
            pc <= 0;
            // Explicitly initialize registers (Verilog-1995 compatible)
            regs[0] = 0; regs[1] = 0; regs[2] = 0; regs[3] = 0;
            regs[4] = 0; regs[5] = 0; regs[6] = 0; regs[7] = 0;
            regs[8] = 0; regs[9] = 0; regs[10] = 0; regs[11] = 0;
            regs[12] = 0; regs[13] = 0; regs[14] = 0; regs[15] = 0;
            regs[16] = 0; regs[17] = 0; regs[18] = 0; regs[19] = 0;
            regs[20] = 0; regs[21] = 0; regs[22] = 0; regs[23] = 0;
            regs[24] = 0; regs[25] = 0; regs[26] = 0; regs[27] = 0;
            regs[28] = 0; regs[29] = 0; regs[30] = 0; regs[31] = 0;
        end else begin
            pc <= pc + 4; // Default increment
            case (opcode)
                7'b0010011: begin // I-type (addi)
                    if (funct3 == 3'b000)
                        regs[rd] = regs[rs1] + imm_i;
                end
                7'b0110011: begin // R-type (add, sub, and, or, sll)
                    case ({funct7, funct3})
                        10'b0000000_000: regs[rd] = regs[rs1] + regs[rs2]; // add
                        10'b0100000_000: regs[rd] = regs[rs1] - regs[rs2]; // sub
                        10'b0000000_111: regs[rd] = regs[rs1] & regs[rs2]; // and
                        10'b0000000_110: regs[rd] = regs[rs1] | regs[rs2]; // or
                        10'b0000000_001: regs[rd] = regs[rs1] << regs[rs2][4:0]; // sll
                    endcase
                end
                7'b0000011: begin // Load (lw)
                    if (funct3 == 3'b010)
                        regs[rd] = mem[(regs[rs1] + imm_i) >> 2];
                end
                7'b0100011: begin // Store (sw)
                    if (funct3 == 3'b010)
                        mem[(regs[rs1] + imm_s) >> 2] = regs[rs2];
                end
                7'b1100011: begin // Branch (beq)
                    if (funct3 == 3'b000 && regs[rs1] == regs[rs2])
                        pc = pc + imm_b - 4;
                end
                7'b1101111: begin // Jump (jal)
                    regs[rd] = pc + 4;
                    pc = pc + imm_j - 4;
                end
                7'b1110011: begin // ecall
                    $display("ECALL: x10 = %d", regs[10]);
                    $finish;
                end
            endcase
            regs[0] = 0; // Ensure x0 is always 0
        end
    end
endmodule

tbnew.v
`timescale 1ns / 1ps

module tbnew;
    reg clk;
    reg reset;
    wire [31:0] pc;
    wire [31:0] x10;

    // Instantiate the DUT
    riscv_core uut (
        .clk(clk),
        .reset(reset),
        .pc(pc),
        .x10(x10)
    );

    // Clock Generation: 10ns period
    always #5 clk = ~clk;

    // Initialize memory from hex file
    initial begin
        $display("Loading firmware...");
        $readmemh("test.hex", uut.mem);
    end

    // Stimulus block
    initial begin
        clk = 0;
        reset = 1;
        #20 reset = 0;
        #200 $display("Simulation completed.");
        $finish;
    end

    // Dump waveform
   initial begin
    $dumpfile("wave.vcd");
    $dumpvars(0, tbnew);
    $dumpvars(0, tbnew.uut);

    // Dump registers x5 to x13 used in test program
    $dumpvars(0, tbnew.uut.regs[5]);  // x5
    $dumpvars(0, tbnew.uut.regs[6]);  // x6
    $dumpvars(0, tbnew.uut.regs[7]);  // x7
    $dumpvars(0, tbnew.uut.regs[8]);  // x8
    $dumpvars(0, tbnew.uut.regs[9]);  // x9
    $dumpvars(0, tbnew.uut.regs[10]); // x10
    $dumpvars(0, tbnew.uut.regs[11]); // x11
    $dumpvars(0, tbnew.uut.regs[12]); // x12
    $dumpvars(0, tbnew.uut.regs[13]); // x13

    // Optional: dump PC and memory interface signals
    $dumpvars(0, tbnew.uut.pc);
   // $dumpvars(0, tbnew.uut.mem_addr);
   // $dumpvars(0, tbnew.uut.mem_wdata);
    //$dumpvars(0, tbnew.uut.mem_rdata);
    //$dumpvars(0, tbnew.uut.trap);
end


endmodule

wave.vcd
$date
	Tue Aug  5 16:11:39 2025
$end
$version
	Icarus Verilog
$end
$timescale
	1ps
$end
$scope module tbnew $end
$var wire 32 ! x10 [31:0] $end
$var wire 32 " pc [31:0] $end
$var reg 1 # clk $end
$var reg 1 $ reset $end
$scope module uut $end
$var wire 1 # clk $end
$var wire 32 % instr [31:0] $end
$var wire 1 $ reset $end
$var wire 32 & x10 [31:0] $end
$var wire 5 ' rs2 [4:0] $end
$var wire 5 ( rs1 [4:0] $end
$var wire 5 ) rd [4:0] $end
$var wire 7 * opcode [6:0] $end
$var wire 32 + imm_s [31:0] $end
$var wire 32 , imm_j [31:0] $end
$var wire 32 - imm_i [31:0] $end
$var wire 32 . imm_b [31:0] $end
$var wire 7 / funct7 [6:0] $end
$var wire 3 0 funct3 [2:0] $end
$var reg 32 1 pc [31:0] $end
$upscope $end
$upscope $end
$scope module tbnew $end
$scope module uut $end
$upscope $end
$upscope $end
$scope module tbnew $end
$scope module uut $end
$var reg 32 2 \regs[5] [31:0] $end
$upscope $end
$upscope $end
$scope module tbnew $end
$scope module uut $end
$var reg 32 3 \regs[6] [31:0] $end
$upscope $end
$upscope $end
$scope module tbnew $end
$scope module uut $end
$var reg 32 4 \regs[7] [31:0] $end
$upscope $end
$upscope $end
$scope module tbnew $end
$scope module uut $end
$var reg 32 5 \regs[8] [31:0] $end
$upscope $end
$upscope $end
$scope module tbnew $end
$scope module uut $end
$var reg 32 6 \regs[9] [31:0] $end
$upscope $end
$upscope $end
$scope module tbnew $end
$scope module uut $end
$var reg 32 7 \regs[10] [31:0] $end
$upscope $end
$upscope $end
$scope module tbnew $end
$scope module uut $end
$var reg 32 8 \regs[11] [31:0] $end
$upscope $end
$upscope $end
$scope module tbnew $end
$scope module uut $end
$var reg 32 9 \regs[12] [31:0] $end
$upscope $end
$upscope $end
$scope module tbnew $end
$scope module uut $end
$var reg 32 : \regs[13] [31:0] $end
$upscope $end
$upscope $end
$enddefinitions $end
#0
$dumpvars
b0 :
b0 9
b0 8
b0 7
b0 6
b0 5
b0 4
b0 3
b0 2
b0 1
b0 0
b0 /
b100000000100 .
b111 -
b100000000110 ,
b101 +
b10011 *
b101 )
b0 (
b111 '
b0 &
b11100000000001010010011 %
1$
0#
b0 "
b0 !
$end
#5000
b0 :
b0 9
b0 8
b0 7
b0 6
b0 5
b0 4
b0 3
b0 2
1#
#10000
0#
#15000
b0 :
b0 9
b0 8
b0 7
b0 6
b0 5
b0 4
b0 3
b0 2
1#
#20000
0#
0$
#25000
b110 .
b110 )
b101 '
b101 -
b110 +
b100000000100 ,
b10100000000001100010011 %
b100 "
b100 1
b111 2
1#
#30000
0#
#35000
b100000000110 .
b110011 *
b111 )
b101 (
b110 '
b110 -
b111 +
b101000000000000110 ,
b11000101000001110110011 %
b1000 "
b1000 1
b101 3
1#
#40000
0#
#45000
b10000001000 .
b1000 )
b111 (
b101 '
b100000 /
b10000000101 -
b10000001000 +
b111000110000000100 ,
b1000000010100111000010000110011 %
b1100 "
b1100 1
b1100 4
1#
#50000
0#
#55000
b100000001000 .
b1001 )
b111 0
b110 '
b0 /
b110 -
b1001 +
b111111000000000110 ,
b11000111111010010110011 %
b10000 "
b10000 1
b101 5
1#
#60000
0#
#65000
b1010 .
b1010 )
b110 0
b1010 +
b111110000000000110 ,
b11000111110010100110011 %
b10100 "
b10100 1
b100 6
1#
#70000
0#
#75000
b100000001010 .
b1011 )
b1 0
b101 (
b1011 +
b101001000000000110 ,
b11000101001010110110011 %
b11000 "
b11000 1
b1101 7
b1101 !
b1101 &
1#
#80000
0#
#85000
b0 .
b100011 *
b0 )
b10 0
b0 (
b1010 '
b1010 -
b0 +
b10000000001010 ,
b101000000010000000100011 %
b11100 "
b11100 1
b11100000 8
1#
#90000
0#
#95000
b1100 .
b11 *
b1100 )
b0 '
b0 -
b1100 +
b10000000000000 ,
b10011000000011 %
b100000 "
b100000 1
1#
#100000
0#
#105000
b1000 .
b1100011 *
b1000 )
b0 0
b1100 (
b1010 '
b1010 -
b1000 +
b1100000000000001010 ,
b101001100000010001100011 %
b100100 "
b100100 1
b1101 9
1#
#110000
0#
#115000
b11111111111111111111011111101010 .
b10011 *
b1010 )
b0 (
b11111 '
b1111111 /
b11111111111111111111111111111111 -
b11111111111111111111111111101010 +
b11111111111100000000111111111110 ,
b11111111111100000000010100010011 %
b101000 "
b101000 1
1#
#120000
0#
#125000
b100000001100 .
b1101111 *
b1101 )
b1000 '
b0 /
b1000 -
b1101 +
b1000 ,
b100000000000011011101111 %
b101100 "
b101100 1
b11111111111111111111111111111111 7
b11111111111111111111111111111111 !
b11111111111111111111111111111111 &
1#
#130000
0#
#135000
b1010 .
b10011 *
b1010 )
b0 '
b0 -
b1010 +
b0 ,
b10100010011 %
b110000 "
b110000 1
b110000 :
1#
#140000
0#
#145000
b110011 *
b1100 (
b1011 '
b1011 -
b1100000100000001010 ,
b101101100000010100110011 %
b110100 "
b110100 1
b0 7
b0 !
b0 &
1#
#150000
0#
#155000
b0 .
b1110011 *
b0 )
b0 (
b0 '
b0 -
b0 +
b0 ,
b1110011 %
b111000 "
b111000 1
b11101101 7
b11101101 !
b11101101 &
1#
#160000
0#
#165000
bx0 .
bx *
bx )
bx 0
bx (
bx '
bx /
bx -
bx +
bx0 ,
bx %
b111100 "
b111100 1
1#
